zohosdk/__init__.py
zohosdk/src/__init__.py
zohosdk/src/json_details.json
zohosdk/src/com/__init__.py
zohosdk/src/com/zoho/__init__.py
zohosdk/src/com/zoho/header.py
zohosdk/src/com/zoho/header_map.py
zohosdk/src/com/zoho/initializer.py
zohosdk/src/com/zoho/param.py
zohosdk/src/com/zoho/parameter_map.py
zohosdk/src/com/zoho/request_proxy.py
zohosdk/src/com/zoho/sdk_config.py
zohosdk/src/com/zoho/user_signature.py
zohosdk/src/com/zoho/api/__init__.py
zohosdk/src/com/zoho/api/authenticator/__init__.py
zohosdk/src/com/zoho/api/authenticator/api_key.py
zohosdk/src/com/zoho/api/authenticator/oauth_token.py
zohosdk/src/com/zoho/api/authenticator/token.py
zohosdk/src/com/zoho/api/authenticator/store/__init__.py
zohosdk/src/com/zoho/api/authenticator/store/db_store.py
zohosdk/src/com/zoho/api/authenticator/store/file_store.py
zohosdk/src/com/zoho/api/authenticator/store/token_store.py
zohosdk/src/com/zoho/api/logger/__init__.py
zohosdk/src/com/zoho/api/logger/logger.py
zohosdk/src/com/zoho/dc/__init__.py
zohosdk/src/com/zoho/dc/au_data_center.py
zohosdk/src/com/zoho/dc/cn_data_center.py
zohosdk/src/com/zoho/dc/data_center.py
zohosdk/src/com/zoho/dc/eu_data_center.py
zohosdk/src/com/zoho/dc/in_data_center.py
zohosdk/src/com/zoho/dc/us_data_center.py
zohosdk/src/com/zoho/examples/writer/create_document.py
zohosdk/src/com/zoho/exception/__init__.py
zohosdk/src/com/zoho/exception/sdk_exception.py
zohosdk/src/com/zoho/officeintegrator/__init__.py
zohosdk/src/com/zoho/officeintegrator/v1/__init__.py
zohosdk/src/com/zoho/officeintegrator/v1/all_sessions_response.py
zohosdk/src/com/zoho/officeintegrator/v1/callback_settings.py
zohosdk/src/com/zoho/officeintegrator/v1/compare_document_parameters.py
zohosdk/src/com/zoho/officeintegrator/v1/compare_document_response.py
zohosdk/src/com/zoho/officeintegrator/v1/convert_presentation_parameters.py
zohosdk/src/com/zoho/officeintegrator/v1/create_document_parameters.py
zohosdk/src/com/zoho/officeintegrator/v1/create_document_response.py
zoi_python_sdk-1.0.2.dist-info/LICENSE
zoi_python_sdk-1.0.2.dist-info/METADATA
zoi_python_sdk-1.0.2.dist-info/WHEEL
zoi_python_sdk-1.0.2.dist-info/top_level.txt
zoi_python_sdk-1.0.2.dist-info/RECORD
